tslearn/__init__.py
tslearn/.cached_datasets/Trace.npz
tslearn/barycenters/__init__.py
tslearn/barycenters/dba.py
tslearn/barycenters/euclidean.py
tslearn/barycenters/softdtw.py
tslearn/barycenters/utils.py
tslearn/bases/__init__.py
tslearn/bases/bases.py
tslearn/clustering/__init__.py
tslearn/clustering/kmeans.py
tslearn/clustering/kshape.py
tslearn/clustering/utils.py
tslearn/datasets/__init__.py
tslearn/datasets/cached.py
tslearn/datasets/datasets.py
tslearn/datasets/ucr_uea.py
tslearn/early_classification/__init__.py
tslearn/early_classification/early_classification.py
tslearn/generators/__init__.py
tslearn/generators/generators.py
tslearn/hdftools/__init__.py
tslearn/hdftools/hdftools.py
tslearn/matrix_profile/__init__.py
tslearn/matrix_profile/matrix_profile.py
tslearn/metrics/__init__.py
tslearn/metrics/ctw.py
tslearn/metrics/cycc.py
tslearn/metrics/cysax.py
tslearn/metrics/dtw_variants.py
tslearn/metrics/sax.py
tslearn/metrics/soft_dtw_fast.py
tslearn/metrics/softdtw_variants.py
tslearn/metrics/utils.py
tslearn/neighbors/__init__.py
tslearn/neighbors/neighbors.py
tslearn/neural_network/__init__.py
tslearn/neural_network/neural_network.py
tslearn/piecewise/__init__.py
tslearn/piecewise/piecewise.py
tslearn/preprocessing/__init__.py
tslearn/preprocessing/preprocessing.py
tslearn/shapelets/__init__.py
tslearn/shapelets/shapelets.py
tslearn/svm/__init__.py
tslearn/svm/svm.py
tslearn/tests/__init__.py
tslearn/tests/sklearn_patches.py
tslearn/tests/test_barycenters.py
tslearn/tests/test_clustering.py
tslearn/tests/test_estimators.py
tslearn/tests/test_matrixprofile.py
tslearn/tests/test_metrics.py
tslearn/tests/test_neighbors.py
tslearn/tests/test_piecewise.py
tslearn/tests/test_preprocessing.py
tslearn/tests/test_serialize_models.py
tslearn/tests/test_shapelets.py
tslearn/tests/test_svm.py
tslearn/tests/test_utils.py
tslearn/tests/test_variablelength.py
tslearn/utils/__init__.py
tslearn/utils/cast.py
tslearn/utils/utils.py
tslearn_m1-0.5.3.dist-info/LICENSE
tslearn_m1-0.5.3.dist-info/METADATA
tslearn_m1-0.5.3.dist-info/WHEEL
tslearn_m1-0.5.3.dist-info/top_level.txt
tslearn_m1-0.5.3.dist-info/RECORD
