Metadata-Version: 2.1
Name: tslearn-m1
Version: 0.5.3
Summary: A machine learning toolkit dedicated to time-series data
Home-page: http://tslearn.readthedocs.io/
Author: Romain Tavenard
Author-email: romain.tavenard@univ-rennes2.fr
License: BSD-2-Clause
Project-URL: Source, https://github.com/tslearn-team/tslearn
License-File: LICENSE
Requires-Dist: numpy
Requires-Dist: scipy
Requires-Dist: scikit-learn
Requires-Dist: numba
Requires-Dist: joblib
Provides-Extra: tests
Requires-Dist: pytest ; extra == 'tests'
